spdstrutil/__init__.py
spdstrutil/data.py
spdstrutil/read.py
spdstrutil/util.py
spdstrutil/write.py
spdstrutil-0.1.2.dist-info/WHEEL
spdstrutil-0.1.2.dist-info/METADATA
spdstrutil-0.1.2.dist-info/RECORD
