Metadata-Version: 2.1
Name: spdstrutil
Version: 0.1.2
Summary: Speedster application utilities package.
Author: dasdias
Author-email: das.dias6@gmail.com
Requires-Python: >=3.9,<4.0
Classifier: Programming Language :: Python :: 3
Classifier: Programming Language :: Python :: 3.10
Classifier: Programming Language :: Python :: 3.9
Requires-Dist: PyYAML (>=6.0,<7.0)
Requires-Dist: loguru (>=0.6.0,<0.7.0)
